brikk/returns/__init__.py
brikk/returns/_errors.py
brikk/returns/_option.py
brikk/returns/_result.py
brikk/returns/_utils.py
brikk/returns/py.typed
brikk_returns-0.4.3.dist-info/WHEEL
brikk_returns-0.4.3.dist-info/METADATA
brikk_returns-0.4.3.dist-info/RECORD
