Metadata-Version: 2.4
Name: brikk-returns
Version: 0.4.3
Summary: brikk-returns
Author: Lucino772
License-Expression: MIT
Requires-Dist: typing-extensions>=4.1.0
Requires-Python: >=3.10
